genipe/__init__.py
genipe/error.py
genipe/version.py
genipe/config/__init__.py
genipe/config/parser.py
genipe/db/__init__.py
genipe/db/utils.py
genipe/formats/__init__.py
genipe/formats/impute2.py
genipe/formats/index.py
genipe/pipeline/__init__.py
genipe/pipeline/arguments.py
genipe/pipeline/cli.py
genipe/reporting/__init__.py
genipe/reporting/autoreport.py
genipe/reporting/utils.py
genipe/reporting/templates/float_template.tex
genipe/reporting/templates/graphics_template.tex
genipe/reporting/templates/iterate_template.tex
genipe/reporting/templates/main_template.tex
genipe/reporting/templates/section_template.tex
genipe/reporting/templates/tabular_template.tex
genipe/reporting/templates/biblio/references.bib
genipe/reporting/templates/biblio/references.bst
genipe/reporting/templates/parts/completion_rate.tex
genipe/reporting/templates/parts/conclusions.tex
genipe/reporting/templates/parts/cross_validation.tex
genipe/reporting/templates/parts/frequencies.tex
genipe/reporting/templates/parts/methods.tex
genipe/reporting/templates/utils/Makefile
genipe/script_templates/run_skat.R
genipe/task/__init__.py
genipe/task/launcher.py
genipe/tests/__init__.py
genipe/tests/__main__.py
genipe/tests/test_arguments.py
genipe/tests/test_db.py
genipe/tests/test_formats.py
genipe/tests/test_impute2_extractor.py
genipe/tests/test_impute2_merger.py
genipe/tests/test_imputed_stats.py
genipe/tests/test_launcher.py
genipe/tests/test_main_pipeline.py
genipe/tests/test_reporting_utils.py
genipe/tests/data/regression_mixedlm.txt.bz2
genipe/tests/data/regression_sim.txt.bz2
genipe/tests/data/regression_sim_inter.txt.bz2
genipe/tests/data/skat_x_matrix.csv.bz2
genipe/tests/data/skat_y_continuous_vector.csv.bz2
genipe/tests/data/skat_y_discrete_vector.csv.bz2
genipe/tests/data/skat_z_matrix.csv.bz2
genipe/tools/__init__.py
genipe/tools/genipe_tutorial.py
genipe/tools/impute2_extractor.py
genipe/tools/impute2_merger.py
genipe/tools/imputed_stats.py
genipe-1.5.0.dist-info/LICENSE.txt
genipe-1.5.0.dist-info/METADATA
genipe-1.5.0.dist-info/WHEEL
genipe-1.5.0.dist-info/entry_points.txt
genipe-1.5.0.dist-info/top_level.txt
genipe-1.5.0.dist-info/RECORD
