Metadata-Version: 2.1
Name: genipe
Version: 1.5.0
Summary: An automatic genome-wide imputation pipeline.
Home-page: https://github.com/pgxcentre/genipe
Author: Louis-Philippe Lemieux Perreault
Author-email: louis-philippe.lemieux.perreault@statgen.org
License: CC BY-NC 4.0
Keywords: bioinformatics imputation pipeline analysis
Platform: UNKNOWN
Classifier: Development Status :: 5 - Production/Stable
Classifier: Intended Audience :: Science/Research
Classifier: License :: Free for non-commercial use
Classifier: Operating System :: Unix
Classifier: Operating System :: POSIX :: Linux
Classifier: Operating System :: MacOS :: MacOS X
Classifier: Programming Language :: Python
Classifier: Programming Language :: Python :: 3.4
Classifier: Programming Language :: Python :: 3.5
Classifier: Topic :: Scientific/Engineering :: Bio-Informatics
Requires-Dist: numpy (>=1.20)
Requires-Dist: Jinja2 (>=2.11)
Requires-Dist: pandas (>=1.2)
Requires-Dist: setuptools (>=12.0.5)
